README.md
setup.py
DEBIAS_M.egg-info/PKG-INFO
DEBIAS_M.egg-info/SOURCES.txt
DEBIAS_M.egg-info/dependency_links.txt
DEBIAS_M.egg-info/requires.txt
DEBIAS_M.egg-info/top_level.txt
debiasm/__init__.py
debiasm/dm_regression.py
debiasm/dmc_multitask_regression.py
debiasm/multiclass.py
debiasm/multitask.py
debiasm/pl_bolt_sklearn_module.py
debiasm/sklearn_functions.py
debiasm/torch_functions.py